pulp_cookbook/__init__.py
pulp_cookbook/metadata.py
pulp_cookbook/app/__init__.py
pulp_cookbook/app/repo_version_utils.py
pulp_cookbook/app/serializers.py
pulp_cookbook/app/utils.py
pulp_cookbook/app/viewsets.py
pulp_cookbook/app/content/__init__.py
pulp_cookbook/app/content/handler.py
pulp_cookbook/app/migrations/0001_initial.py
pulp_cookbook/app/migrations/0002_move_data_to_new_master_distribution_model.py
pulp_cookbook/app/migrations/0003_json_fields.py
pulp_cookbook/app/migrations/__init__.py
pulp_cookbook/app/models/__init__.py
pulp_cookbook/app/models/content.py
pulp_cookbook/app/models/publication.py
pulp_cookbook/app/models/repository.py
pulp_cookbook/app/tasks/__init__.py
pulp_cookbook/app/tasks/publishing.py
pulp_cookbook/app/tasks/synchronizing.py
pulp_cookbook/app/webserver_snippets/__init__.py
pulp_cookbook/app/webserver_snippets/apache.conf
pulp_cookbook/app/webserver_snippets/nginx.conf
pulp_cookbook/tests/__init__.py
pulp_cookbook/tests/functional/__init__.py
pulp_cookbook/tests/functional/constants.py
pulp_cookbook/tests/functional/api/__init__.py
pulp_cookbook/tests/functional/api/test_crud_content_unit.py
pulp_cookbook/tests/functional/api/test_crud_remotes.py
pulp_cookbook/tests/functional/api/test_download_content.py
pulp_cookbook/tests/functional/api/test_publish.py
pulp_cookbook/tests/functional/api/test_sync.py
pulp_cookbook/tests/functional/api/utils.py
pulp_cookbook/tests/unit/__init__.py
pulp_cookbook/tests/unit/test_content.py
pulp_cookbook/tests/unit/test_contentview.py
pulp_cookbook/tests/unit/test_publishing.py
pulp_cookbook/tests/unit/test_synchronizing.py
pulp_cookbook-0.1.0b9.dist-info/LICENSE
pulp_cookbook-0.1.0b9.dist-info/METADATA
pulp_cookbook-0.1.0b9.dist-info/WHEEL
pulp_cookbook-0.1.0b9.dist-info/entry_points.txt
pulp_cookbook-0.1.0b9.dist-info/top_level.txt
pulp_cookbook-0.1.0b9.dist-info/RECORD
