Metadata-Version: 2.1
Name: pulp-cookbook
Version: 0.1.0b9
Summary: Cookbook plugin for the Pulp Project
Home-page: https://github.com/pulp/pulp_cookbook/
Author: Simon Baatz
Author-email: gmbnomis@gmail.com
License: UNKNOWN
Platform: UNKNOWN
Classifier: License :: OSI Approved :: GNU General Public License v2 or later (GPLv2+)
Classifier: Operating System :: POSIX :: Linux
Classifier: Development Status :: 4 - Beta
Classifier: Framework :: Django
Classifier: Programming Language :: Python
Classifier: Programming Language :: Python :: 3
Classifier: Programming Language :: Python :: 3.8
Classifier: Programming Language :: Python :: 3.9
Requires-Dist: pulpcore (>=3.16)
